{
  "image": {
    "filename": "image.jpg",
    "width": 3328,
    "height": 4992
  },
  "lines": [
    {
      "boundary": [
        [
          1538,
          710
        ],
        [
          2850,
          710
        ],
        [
          2850,
          793
        ],
        [
          1538,
          793
        ]
      ],
      "syllables": [
        {
          "text": "tu-",
          "boundary": [
            [
              1912,
              740
            ],
            [
              2005,
              740
            ],
            [
              2005,
              772
            ],
            [
              1912,
              772
            ]
          ]
        },
        {
          "text": "di-",
          "boundary": [
            [
              1651,
              710
            ],
            [
              1721,
              710
            ],
            [
              1721,
              773
            ],
            [
              1651,
              773
            ]
          ]
        },
        {
          "text": "am",
          "boundary": [
            [
              1726,
              739
            ],
            [
              1832,
              739
            ],
            [
              1832,
              774
            ],
            [
              1726,
              774
            ]
          ]
        },
        {
          "text": "cor-",
          "boundary": [
            [
              1538,
              741
            ],
            [
              1648,
              741
            ],
            [
              1648,
              778
            ],
            [
              1538,
              778
            ]
          ]
        },
        {
          "text": "am",
          "boundary": [
            [
              2235,
              748
            ],
            [
              2355,
              748
            ],
            [
              2355,
              785
            ],
            [
              2235,
              785
            ]
          ]
        },
        {
          "text": "et",
          "boundary": [
            [
              2448,
              735
            ],
            [
              2520,
              735
            ],
            [
              2520,
              787
            ],
            [
              2448,
              787
            ]
          ]
        },
        {
          "text": "lu-",
          "boundary": [
            [
              2607,
              729
            ],
            [
              2672,
              729
            ],
            [
              2672,
              789
            ],
            [
              2607,
              789
            ]
          ]
        },
        {
          "text": "ta-",
          "boundary": [
            [
              2682,
              759
            ],
            [
              2755,
              759
            ],
            [
              2755,
              790
            ],
            [
              2682,
              790
            ]
          ]
        },
        {
          "text": "re",
          "boundary": [
            [
              2759,
              756
            ],
            [
              2850,
              756
            ],
            [
              2850,
              793
            ],
            [
              2759,
              793
            ]
          ]
        },
        {
          "text": "sa-",
          "boundary": [
            [
              2533,
              735
            ],
            [
              2598,
              735
            ],
            [
              2598,
              793
            ],
            [
              2533,
              793
            ]
          ]
        }
      ]
    },
    {
      "boundary": [
        [
          1519,
          934
        ],
        [
          2601,
          934
        ],
        [
          2601,
          996
        ],
        [
          1519,
          996
        ]
      ],
      "syllables": [
        {
          "text": "da",
          "boundary": [
            [
              2214,
              952
            ],
            [
              2327,
              952
            ],
            [
              2327,
              995
            ],
            [
              2214,
              995
            ]
          ]
        },
        {
          "text": "tu-",
          "boundary": [
            [
              1519,
              960
            ],
            [
              1620,
              960
            ],
            [
              1620,
              995
            ],
            [
              1519,
              995
            ]
          ]
        },
        {
          "text": "um",
          "boundary": [
            [
              1654,
              961
            ],
            [
              1771,
              961
            ],
            [
              1771,
              995
            ],
            [
              1654,
              995
            ]
          ]
        },
        {
          "text": "no-",
          "boundary": [
            [
              2394,
              961
            ],
            [
              2482,
              961
            ],
            [
              2482,
              996
            ],
            [
              2394,
              996
            ]
          ]
        },
        {
          "text": "bis",
          "boundary": [
            [
              2492,
              934
            ],
            [
              2601,
              934
            ],
            [
              2601,
              996
            ],
            [
              2492,
              996
            ]
          ]
        }
      ]
    },
    {
      "boundary": [
        [
          1464,
          1103
        ],
        [
          2908,
          1103
        ],
        [
          2908,
          1195
        ],
        [
          1464,
          1195
        ]
      ],
      "syllables": [
        {
          "text": "do-",
          "boundary": [
            [
              1966,
              1134
            ],
            [
              2056,
              1134
            ],
            [
              2056,
              1169
            ],
            [
              1966,
              1169
            ]
          ]
        },
        {
          "text": "ti",
          "boundary": [
            [
              1839,
              1137
            ],
            [
              1895,
              1137
            ],
            [
              1895,
              1170
            ],
            [
              1839,
              1170
            ]
          ]
        },
        {
          "text": "di-",
          "boundary": [
            [
              1668,
              1113
            ],
            [
              1740,
              1113
            ],
            [
              1740,
              1174
            ],
            [
              1668,
              1174
            ]
          ]
        },
        {
          "text": "ne-",
          "boundary": [
            [
              1576,
              1139
            ],
            [
              1664,
              1139
            ],
            [
              1664,
              1178
            ],
            [
              1576,
              1178
            ]
          ]
        },
        {
          "text": "xis-",
          "boundary": [
            [
              1747,
              1116
            ],
            [
              1846,
              1116
            ],
            [
              1846,
              1178
            ],
            [
              1747,
              1178
            ]
          ]
        },
        {
          "text": "mi-",
          "boundary": [
            [
              2687,
              1154
            ],
            [
              2783,
              1154
            ],
            [
              2783,
              1184
            ],
            [
              2687,
              1184
            ]
          ]
        },
        {
          "text": "ne",
          "boundary": [
            [
              2805,
              1152
            ],
            [
              2908,
              1152
            ],
            [
              2908,
              1185
            ],
            [
              2805,
              1185
            ]
          ]
        },
        {
          "text": "Be-",
          "boundary": [
            [
              1464,
              1103
            ],
            [
              1570,
              1103
            ],
            [
              1570,
              1195
            ],
            [
              1464,
              1195
            ]
          ]
        }
      ]
    },
    {
      "boundary": [
        [
          1525,
          1322
        ],
        [
          2789,
          1322
        ],
        [
          2789,
          1395
        ],
        [
          1525,
          1395
        ]
      ],
      "syllables": [
        {
          "text": "ter-",
          "boundary": [
            [
              1525,
              1322
            ],
            [
              1670,
              1322
            ],
            [
              1670,
              1379
            ],
            [
              1525,
              1379
            ]
          ]
        },
        {
          "text": "ram",
          "boundary": [
            [
              1864,
              1348
            ],
            [
              2004,
              1348
            ],
            [
              2004,
              1383
            ],
            [
              1864,
              1383
            ]
          ]
        },
        {
          "text": "tu-",
          "boundary": [
            [
              2059,
              1353
            ],
            [
              2158,
              1353
            ],
            [
              2158,
              1385
            ],
            [
              2059,
              1385
            ]
          ]
        },
        {
          "text": "ti",
          "boundary": [
            [
              2737,
              1345
            ],
            [
              2789,
              1345
            ],
            [
              2789,
              1390
            ],
            [
              2737,
              1390
            ]
          ]
        },
        {
          "text": "am",
          "boundary": [
            [
              2396,
              1357
            ],
            [
              2509,
              1357
            ],
            [
              2509,
              1394
            ],
            [
              2396,
              1394
            ]
          ]
        },
        {
          "text": "a-",
          "boundary": [
            [
              2559,
              1357
            ],
            [
              2605,
              1357
            ],
            [
              2605,
              1394
            ],
            [
              2559,
              1394
            ]
          ]
        },
        {
          "text": "ves-",
          "boundary": [
            [
              2623,
              1323
            ],
            [
              2733,
              1323
            ],
            [
              2733,
              1395
            ],
            [
              2623,
              1395
            ]
          ]
        }
      ]
    },
    {
      "boundary": [
        [
          1534,
          1485
        ],
        [
          2619,
          1485
        ],
        [
          2619,
          1557
        ],
        [
          1534,
          1557
        ]
      ],
      "syllables": [
        {
          "text": "vi-",
          "boundary": [
            [
              2013,
              1513
            ],
            [
              2088,
              1513
            ],
            [
              2088,
              1547
            ],
            [
              2013,
              1547
            ]
          ]
        },
        {
          "text": "ti-",
          "boundary": [
            [
              1943,
              1513
            ],
            [
              2004,
              1513
            ],
            [
              2004,
              1549
            ],
            [
              1943,
              1549
            ]
          ]
        },
        {
          "text": "ta-",
          "boundary": [
            [
              2090,
              1516
            ],
            [
              2163,
              1516
            ],
            [
              2163,
              1549
            ],
            [
              2090,
              1549
            ]
          ]
        },
        {
          "text": "cob.",
          "boundary": [
            [
              2479,
              1490
            ],
            [
              2619,
              1490
            ],
            [
              2619,
              1550
            ],
            [
              2479,
              1550
            ]
          ]
        },
        {
          "text": "cap-",
          "boundary": [
            [
              1826,
              1510
            ],
            [
              1948,
              1510
            ],
            [
              1948,
              1551
            ],
            [
              1826,
              1551
            ]
          ]
        },
        {
          "text": "ja-",
          "boundary": [
            [
              2396,
              1515
            ],
            [
              2473,
              1515
            ],
            [
              2473,
              1552
            ],
            [
              2396,
              1552
            ]
          ]
        },
        {
          "text": "tem",
          "boundary": [
            [
              2169,
              1515
            ],
            [
              2311,
              1515
            ],
            [
              2311,
              1556
            ],
            [
              2169,
              1556
            ]
          ]
        },
        {
          "text": "sti",
          "boundary": [
            [
              1534,
              1485
            ],
            [
              1625,
              1485
            ],
            [
              1625,
              1557
            ],
            [
              1534,
              1557
            ]
          ]
        }
      ]
    },
    {
      "boundary": [
        [
          2432,
          1786
        ],
        [
          2839,
          1788
        ],
        [
          2845,
          1774
        ],
        [
          2839,
          1683
        ],
        [
          2618,
          1655
        ],
        [
          2615,
          1655
        ],
        [
          2484,
          1680
        ],
        [
          2432,
          1658
        ],
        [
          2432,
          1777
        ],
        [
          2432,
          1786
        ]
      ],
      "syllables": [
        {
          "text": "ni-",
          "boundary": [
            [
              2828,
              1714
            ],
            [
              2898,
              1714
            ],
            [
              2898,
              1751
            ],
            [
              2828,
              1751
            ]
          ]
        },
        {
          "text": "a.",
          "boundary": [
            [
              2898,
              1698
            ],
            [
              2981,
              1698
            ],
            [
              2981,
              1757
            ],
            [
              2898,
              1757
            ]
          ]
        },
        {
          "text": "De-",
          "boundary": [
            [
              2511,
              1786
            ],
            [
              2511,
              1675
            ],
            [
              2484,
              1680
            ],
            [
              2432,
              1658
            ],
            [
              2432,
              1777
            ],
            [
              2432,
              1786
            ]
          ]
        },
        {
          "text": "ce",
          "boundary": [
            [
              2582,
              1787
            ],
            [
              2582,
              1661
            ],
            [
              2511,
              1675
            ],
            [
              2511,
              1786
            ]
          ]
        },
        {
          "text": "do-",
          "boundary": [
            [
              2622,
              1787
            ],
            [
              2622,
              1656
            ],
            [
              2618,
              1655
            ],
            [
              2615,
              1655
            ],
            [
              2598,
              1658
            ],
            [
              2598,
              1787
            ]
          ]
        },
        {
          "text": "mi-",
          "boundary": [
            [
              2645,
              1787
            ],
            [
              2645,
              1658
            ],
            [
              2622,
              1656
            ],
            [
              2622,
              1787
            ]
          ]
        },
        {
          "text": "nus",
          "boundary": [
            [
              2725,
              1787
            ],
            [
              2725,
              1669
            ],
            [
              2645,
              1658
            ],
            [
              2645,
              1787
            ]
          ]
        },
        {
          "text": "Os",
          "boundary": [
            [
              1467,
              1788
            ],
            [
              1591,
              1788
            ],
            [
              1591,
              1650
            ],
            [
              1580,
              1647
            ],
            [
              1578,
              1647
            ],
            [
              1575,
              1647
            ],
            [
              1467,
              1655
            ],
            [
              1467,
              1774
            ]
          ]
        },
        {
          "text": "tu",
          "boundary": [
            [
              1699,
              1788
            ],
            [
              1699,
              1673
            ],
            [
              1688,
              1675
            ],
            [
              1608,
              1654
            ],
            [
              1608,
              1788
            ]
          ]
        },
        {
          "text": "con-",
          "boundary": [
            [
              1840,
              1788
            ],
            [
              1840,
              1677
            ],
            [
              1808,
              1677
            ],
            [
              1786,
              1658
            ],
            [
              1786,
              1655
            ],
            [
              1783,
              1655
            ],
            [
              1780,
              1655
            ],
            [
              1777,
              1655
            ],
            [
              1715,
              1669
            ],
            [
              1715,
              1788
            ]
          ]
        },
        {
          "text": "ves-",
          "boundary": [
            [
              1947,
              1788
            ],
            [
              1947,
              1647
            ],
            [
              1930,
              1647
            ],
            [
              1927,
              1647
            ],
            [
              1924,
              1647
            ],
            [
              1921,
              1647
            ],
            [
              1921,
              1650
            ],
            [
              1891,
              1677
            ],
            [
              1840,
              1677
            ],
            [
              1840,
              1788
            ]
          ]
        },
        {
          "text": "tens",
          "boundary": [
            [
              2104,
              1788
            ],
            [
              2104,
              1661
            ],
            [
              2057,
              1677
            ],
            [
              2016,
              1677
            ],
            [
              1988,
              1650
            ],
            [
              1988,
              1647
            ],
            [
              1985,
              1647
            ],
            [
              1982,
              1647
            ],
            [
              1947,
              1647
            ],
            [
              1947,
              1788
            ]
          ]
        },
        {
          "text": "Aco",
          "boundary": [
            [
              2360,
              1788
            ],
            [
              2360,
              1774
            ],
            [
              2360,
              1677
            ],
            [
              2152,
              1647
            ],
            [
              2149,
              1647
            ],
            [
              2146,
              1647
            ],
            [
              2129,
              1653
            ],
            [
              2129,
              1788
            ]
          ]
        },
        {
          "text": "ve-",
          "boundary": [
            [
              2839,
              1788
            ],
            [
              2845,
              1774
            ],
            [
              2839,
              1683
            ],
            [
              2748,
              1671
            ],
            [
              2748,
              1788
            ]
          ]
        }
      ]
    },
    {
      "boundary": [
        [
          1729,
          1864
        ],
        [
          2911,
          1864
        ],
        [
          2911,
          1940
        ],
        [
          1729,
          1940
        ]
      ],
      "syllables": [
        {
          "text": "Sab-",
          "boundary": [
            [
              1729,
              1864
            ],
            [
              1912,
              1864
            ],
            [
              1912,
              1936
            ],
            [
              1729,
              1936
            ]
          ]
        },
        {
          "text": "XII",
          "boundary": [
            [
              2438,
              1883
            ],
            [
              2598,
              1883
            ],
            [
              2598,
              1938
            ],
            [
              2438,
              1938
            ]
          ]
        },
        {
          "text": "Lect.",
          "boundary": [
            [
              2666,
              1878
            ],
            [
              2911,
              1878
            ],
            [
              2911,
              1938
            ],
            [
              2666,
              1938
            ]
          ]
        },
        {
          "text": "ba-",
          "boundary": [
            [
              1940,
              1869
            ],
            [
              2058,
              1869
            ],
            [
              2058,
              1939
            ],
            [
              1940,
              1939
            ]
          ]
        },
        {
          "text": "to",
          "boundary": [
            [
              2075,
              1870
            ],
            [
              2190,
              1870
            ],
            [
              2190,
              1939
            ],
            [
              2075,
              1939
            ]
          ]
        },
        {
          "text": "in",
          "boundary": [
            [
              2245,
              1875
            ],
            [
              2361,
              1875
            ],
            [
              2361,
              1940
            ],
            [
              2245,
              1940
            ]
          ]
        }
      ]
    },
    {
      "boundary": [
        [
          1468,
          1989
        ],
        [
          2447,
          1989
        ],
        [
          2447,
          2172
        ],
        [
          1468,
          2172
        ]
      ],
      "syllables": [
        {
          "text": "ni",
          "boundary": [
            [
              1707,
              2091
            ],
            [
              1791,
              2091
            ],
            [
              1791,
              2127
            ],
            [
              1707,
              2127
            ]
          ]
        },
        {
          "text": "et",
          "boundary": [
            [
              1837,
              2067
            ],
            [
              1914,
              2067
            ],
            [
              1914,
              2127
            ],
            [
              1837,
              2127
            ]
          ]
        },
        {
          "text": "ten-",
          "boundary": [
            [
              2007,
              2079
            ],
            [
              2117,
              2079
            ],
            [
              2117,
              2128
            ],
            [
              2007,
              2128
            ]
          ]
        },
        {
          "text": "os-",
          "boundary": [
            [
              1929,
              2073
            ],
            [
              2005,
              2073
            ],
            [
              2005,
              2130
            ],
            [
              1929,
              2130
            ]
          ]
        },
        {
          "text": "de",
          "boundary": [
            [
              2130,
              2064
            ],
            [
              2222,
              2064
            ],
            [
              2222,
              2130
            ],
            [
              2130,
              2130
            ]
          ]
        },
        {
          "text": "no-",
          "boundary": [
            [
              2238,
              2096
            ],
            [
              2333,
              2096
            ],
            [
              2333,
              2131
            ],
            [
              2238,
              2131
            ]
          ]
        },
        {
          "text": "bis.",
          "boundary": [
            [
              2335,
              2066
            ],
            [
              2447,
              2066
            ],
            [
              2447,
              2134
            ],
            [
              2335,
              2134
            ]
          ]
        },
        {
          "text": "Ve-",
          "boundary": [
            [
              1468,
              1989
            ],
            [
              1703,
              1989
            ],
            [
              1703,
              2172
            ],
            [
              1468,
              2172
            ]
          ]
        }
      ]
    },
    {
      "boundary": [
        [
          1427,
          2253
        ],
        [
          2953,
          2253
        ],
        [
          2953,
          2384
        ],
        [
          1427,
          2384
        ]
      ],
      "syllables": [
        {
          "text": "mo",
          "boundary": [
            [
              1712,
              2283
            ],
            [
              1815,
              2283
            ],
            [
              1815,
              2315
            ],
            [
              1712,
              2315
            ]
          ]
        },
        {
          "text": "cae",
          "boundary": [
            [
              1851,
              2280
            ],
            [
              1971,
              2280
            ],
            [
              1971,
              2318
            ],
            [
              1851,
              2318
            ]
          ]
        },
        {
          "text": "e-",
          "boundary": [
            [
              2162,
              2280
            ],
            [
              2203,
              2280
            ],
            [
              2203,
              2318
            ],
            [
              2162,
              2318
            ]
          ]
        },
        {
          "text": "lo",
          "boundary": [
            [
              2009,
              2253
            ],
            [
              2085,
              2253
            ],
            [
              2085,
              2321
            ],
            [
              2009,
              2321
            ]
          ]
        },
        {
          "text": "sio",
          "boundary": [
            [
              2368,
              2260
            ],
            [
              2457,
              2260
            ],
            [
              2457,
              2322
            ],
            [
              2368,
              2322
            ]
          ]
        },
        {
          "text": "ei-",
          "boundary": [
            [
              2503,
              2280
            ],
            [
              2581,
              2280
            ],
            [
              2581,
              2322
            ],
            [
              2503,
              2322
            ]
          ]
        },
        {
          "text": "us",
          "boundary": [
            [
              2578,
              2269
            ],
            [
              2687,
              2269
            ],
            [
              2687,
              2326
            ],
            [
              2578,
              2326
            ]
          ]
        },
        {
          "text": "et",
          "boundary": [
            [
              2874,
              2273
            ],
            [
              2953,
              2273
            ],
            [
              2953,
              2328
            ],
            [
              2874,
              2328
            ]
          ]
        },
        {
          "text": "sum-",
          "boundary": [
            [
              1560,
              2262
            ],
            [
              1702,
              2262
            ],
            [
              1702,
              2330
            ],
            [
              1560,
              2330
            ]
          ]
        },
        {
          "text": "gres-",
          "boundary": [
            [
              2212,
              2261
            ],
            [
              2365,
              2261
            ],
            [
              2365,
              2358
            ],
            [
              2212,
              2358
            ]
          ]
        },
        {
          "text": "A",
          "boundary": [
            [
              1427,
              2253
            ],
            [
              1555,
              2253
            ],
            [
              1555,
              2384
            ],
            [
              1427,
              2384
            ]
          ]
        }
      ]
    },
    {
      "boundary": [
        [
          1541,
          2444
        ],
        [
          2891,
          2444
        ],
        [
          2891,
          2521
        ],
        [
          1541,
          2521
        ]
      ],
      "syllables": [
        {
          "text": "cur-",
          "boundary": [
            [
              1613,
              2463
            ],
            [
              1742,
              2463
            ],
            [
              1742,
              2504
            ],
            [
              1613,
              2504
            ]
          ]
        },
        {
          "text": "oc-",
          "boundary": [
            [
              1541,
              2468
            ],
            [
              1622,
              2468
            ],
            [
              1622,
              2505
            ],
            [
              1541,
              2505
            ]
          ]
        },
        {
          "text": "ei-",
          "boundary": [
            [
              1918,
              2461
            ],
            [
              1998,
              2461
            ],
            [
              1998,
              2509
            ],
            [
              1918,
              2509
            ]
          ]
        },
        {
          "text": "sus",
          "boundary": [
            [
              1745,
              2444
            ],
            [
              1870,
              2444
            ],
            [
              1870,
              2510
            ],
            [
              1745,
              2510
            ]
          ]
        },
        {
          "text": "us-",
          "boundary": [
            [
              2325,
              2455
            ],
            [
              2417,
              2455
            ],
            [
              2417,
              2511
            ],
            [
              2325,
              2511
            ]
          ]
        },
        {
          "text": "us",
          "boundary": [
            [
              1991,
              2459
            ],
            [
              2089,
              2459
            ],
            [
              2089,
              2512
            ],
            [
              1991,
              2512
            ]
          ]
        },
        {
          "text": "ad",
          "boundary": [
            [
              2611,
              2455
            ],
            [
              2713,
              2455
            ],
            [
              2713,
              2514
            ],
            [
              2611,
              2514
            ]
          ]
        },
        {
          "text": "sum",
          "boundary": [
            [
              2740,
              2461
            ],
            [
              2891,
              2461
            ],
            [
              2891,
              2520
            ],
            [
              2740,
              2520
            ]
          ]
        },
        {
          "text": "que",
          "boundary": [
            [
              2421,
              2464
            ],
            [
              2550,
              2464
            ],
            [
              2550,
              2521
            ],
            [
              2421,
              2521
            ]
          ]
        }
      ]
    },
    {
      "boundary": [
        [
          1544,
          2631
        ],
        [
          1977,
          2631
        ],
        [
          1977,
          2696
        ],
        [
          1544,
          2696
        ]
      ],
      "syllables": [
        {
          "text": "mum",
          "boundary": [
            [
              1544,
              2654
            ],
            [
              1734,
              2654
            ],
            [
              1734,
              2692
            ],
            [
              1544,
              2692
            ]
          ]
        },
        {
          "text": "eius.",
          "boundary": [
            [
              1812,
              2631
            ],
            [
              1977,
              2631
            ],
            [
              1977,
              2696
            ],
            [
              1812,
              2696
            ]
          ]
        }
      ]
    },
    {
      "boundary": [
        [
          1333,
          2809
        ],
        [
          2979,
          2809
        ],
        [
          2979,
          2933
        ],
        [
          1333,
          2933
        ]
      ],
      "syllables": [
        {
          "text": "li",
          "boundary": [
            [
              1617,
              2809
            ],
            [
              1675,
              2809
            ],
            [
              1675,
              2871
            ],
            [
              1617,
              2871
            ]
          ]
        },
        {
          "text": "e-",
          "boundary": [
            [
              1717,
              2835
            ],
            [
              1765,
              2835
            ],
            [
              1765,
              2872
            ],
            [
              1717,
              2872
            ]
          ]
        },
        {
          "text": "nar-",
          "boundary": [
            [
              1766,
              2837
            ],
            [
              1855,
              2837
            ],
            [
              1855,
              2876
            ],
            [
              1766,
              2876
            ]
          ]
        },
        {
          "text": "",
          "boundary": [
            [
              1333,
              2819
            ],
            [
              1416,
              2819
            ],
            [
              1416,
              2877
            ],
            [
              1333,
              2877
            ]
          ]
        },
        {
          "text": "Cae-",
          "boundary": [
            [
              1450,
              2816
            ],
            [
              1610,
              2816
            ],
            [
              1610,
              2897
            ],
            [
              1450,
              2897
            ]
          ]
        },
        {
          "text": "rant",
          "boundary": [
            [
              2378,
              2845
            ],
            [
              2571,
              2845
            ],
            [
              2571,
              2900
            ],
            [
              2378,
              2900
            ]
          ]
        },
        {
          "text": "ri",
          "boundary": [
            [
              2886,
              2842
            ],
            [
              2979,
              2842
            ],
            [
              2979,
              2900
            ],
            [
              2886,
              2900
            ]
          ]
        },
        {
          "text": "glo",
          "boundary": [
            [
              2662,
              2830
            ],
            [
              2793,
              2830
            ],
            [
              2793,
              2933
            ],
            [
              2662,
              2933
            ]
          ]
        }
      ]
    },
    {
      "boundary": [
        [
          1529,
          3004
        ],
        [
          3025,
          3004
        ],
        [
          3025,
          3102
        ],
        [
          1529,
          3102
        ]
      ],
      "syllables": [
        {
          "text": "am",
          "boundary": [
            [
              1529,
              3037
            ],
            [
              1643,
              3037
            ],
            [
              1643,
              3074
            ],
            [
              1529,
              3074
            ]
          ]
        },
        {
          "text": "de-",
          "boundary": [
            [
              1686,
              3004
            ],
            [
              1785,
              3004
            ],
            [
              1785,
              3074
            ],
            [
              1686,
              3074
            ]
          ]
        },
        {
          "text": "i",
          "boundary": [
            [
              2221,
              3049
            ],
            [
              2246,
              3049
            ],
            [
              2246,
              3084
            ],
            [
              2221,
              3084
            ]
          ]
        },
        {
          "text": "et",
          "boundary": [
            [
              2327,
              3029
            ],
            [
              2409,
              3029
            ],
            [
              2409,
              3092
            ],
            [
              2327,
              3092
            ]
          ]
        },
        {
          "text": "opera",
          "boundary": [
            [
              2423,
              3030
            ],
            [
              2653,
              3030
            ],
            [
              2653,
              3100
            ],
            [
              2423,
              3100
            ]
          ]
        },
        {
          "text": "manuum",
          "boundary": [
            [
              2700,
              3034
            ],
            [
              3025,
              3034
            ],
            [
              3025,
              3102
            ],
            [
              2700,
              3102
            ]
          ]
        }
      ]
    },
    {
      "boundary": [
        [
          1533,
          3205
        ],
        [
          2996,
          3205
        ],
        [
          2996,
          3287
        ],
        [
          1533,
          3287
        ]
      ],
      "syllables": [
        {
          "text": "e",
          "boundary": [
            [
              1533,
              3220
            ],
            [
              1580,
              3220
            ],
            [
              1580,
              3259
            ],
            [
              1533,
              3259
            ]
          ]
        },
        {
          "text": "ius",
          "boundary": [
            [
              1747,
              3206
            ],
            [
              1873,
              3206
            ],
            [
              1873,
              3264
            ],
            [
              1747,
              3264
            ]
          ]
        },
        {
          "text": "ad",
          "boundary": [
            [
              2038,
              3211
            ],
            [
              2146,
              3211
            ],
            [
              2146,
              3268
            ],
            [
              2038,
              3268
            ]
          ]
        },
        {
          "text": "nuntiat",
          "boundary": [
            [
              2153,
              3224
            ],
            [
              2445,
              3224
            ],
            [
              2445,
              3274
            ],
            [
              2153,
              3274
            ]
          ]
        },
        {
          "text": "fi",
          "boundary": [
            [
              2478,
              3205
            ],
            [
              2529,
              3205
            ],
            [
              2529,
              3275
            ],
            [
              2478,
              3275
            ]
          ]
        },
        {
          "text": "rmamentum",
          "boundary": [
            [
              2532,
              3228
            ],
            [
              2996,
              3228
            ],
            [
              2996,
              3287
            ],
            [
              2532,
              3287
            ]
          ]
        }
      ]
    },
    {
      "boundary": [
        [
          1445,
          3379
        ],
        [
          2885,
          3379
        ],
        [
          2885,
          3481
        ],
        [
          1445,
          3481
        ]
      ],
      "syllables": [
        {
          "text": "utt",
          "boundary": [
            [
              1937,
              3412
            ],
            [
              2042,
              3412
            ],
            [
              2042,
              3449
            ],
            [
              1937,
              3449
            ]
          ]
        },
        {
          "text": "s",
          "boundary": [
            [
              1900,
              3390
            ],
            [
              1937,
              3390
            ],
            [
              1937,
              3452
            ],
            [
              1900,
              3452
            ]
          ]
        },
        {
          "text": "n",
          "boundary": [
            [
              1532,
              3416
            ],
            [
              1580,
              3416
            ],
            [
              1580,
              3453
            ],
            [
              1532,
              3453
            ]
          ]
        },
        {
          "text": "sole",
          "boundary": [
            [
              1591,
              3385
            ],
            [
              1740,
              3385
            ],
            [
              1740,
              3455
            ],
            [
              1591,
              3455
            ]
          ]
        },
        {
          "text": "cukum",
          "boundary": [
            [
              2485,
              3409
            ],
            [
              2726,
              3409
            ],
            [
              2726,
              3457
            ],
            [
              2485,
              3457
            ]
          ]
        },
        {
          "text": "su",
          "boundary": [
            [
              2778,
              3396
            ],
            [
              2885,
              3396
            ],
            [
              2885,
              3463
            ],
            [
              2778,
              3463
            ]
          ]
        },
        {
          "text": "taberna",
          "boundary": [
            [
              2121,
              3407
            ],
            [
              2444,
              3407
            ],
            [
              2444,
              3468
            ],
            [
              2121,
              3468
            ]
          ]
        },
        {
          "text": "po",
          "boundary": [
            [
              1787,
              3410
            ],
            [
              1876,
              3410
            ],
            [
              1876,
              3469
            ],
            [
              1787,
              3469
            ]
          ]
        },
        {
          "text": "I",
          "boundary": [
            [
              1445,
              3379
            ],
            [
              1503,
              3379
            ],
            [
              1503,
              3481
            ],
            [
              1445,
              3481
            ]
          ]
        }
      ]
    },
    {
      "boundary": [
        [
          2215,
          3660
        ],
        [
          2215,
          3674
        ],
        [
          2875,
          3680
        ],
        [
          2878,
          3658
        ],
        [
          2870,
          3552
        ],
        [
          2349,
          3566
        ],
        [
          2310,
          3552
        ],
        [
          2307,
          3552
        ],
        [
          2304,
          3552
        ],
        [
          2213,
          3569
        ],
        [
          2215,
          3660
        ]
      ],
      "syllables": [
        {
          "text": "um",
          "boundary": [
            [
              1534,
              3592
            ],
            [
              1650,
              3592
            ],
            [
              1650,
              3630
            ],
            [
              1534,
              3630
            ]
          ]
        },
        {
          "text": "et",
          "boundary": [
            [
              2118,
              3583
            ],
            [
              2208,
              3583
            ],
            [
              2208,
              3637
            ],
            [
              2118,
              3637
            ]
          ]
        },
        {
          "text": "spon",
          "boundary": [
            [
              2833,
              3563
            ],
            [
              2995,
              3563
            ],
            [
              2995,
              3640
            ],
            [
              2833,
              3640
            ]
          ]
        },
        {
          "text": "ip-",
          "boundary": [
            [
              2215,
              3674
            ],
            [
              2291,
              3675
            ],
            [
              2291,
              3554
            ],
            [
              2213,
              3569
            ],
            [
              2215,
              3660
            ]
          ]
        },
        {
          "text": "se",
          "boundary": [
            [
              2397,
              3676
            ],
            [
              2397,
              3565
            ],
            [
              2349,
              3566
            ],
            [
              2310,
              3552
            ],
            [
              2307,
              3552
            ],
            [
              2304,
              3552
            ],
            [
              2291,
              3554
            ],
            [
              2291,
              3675
            ]
          ]
        },
        {
          "text": "tam",
          "boundary": [
            [
              2585,
              3677
            ],
            [
              2585,
              3560
            ],
            [
              2427,
              3564
            ],
            [
              2427,
              3676
            ]
          ]
        },
        {
          "text": "quam",
          "boundary": [
            [
              2827,
              3680
            ],
            [
              2827,
              3553
            ],
            [
              2600,
              3559
            ],
            [
              2600,
              3678
            ]
          ]
        }
      ]
    }
  ],
  "neumes": [
    {
      "type": "punctum",
      "bbox": {
        "x": 2807,
        "y": 2430,
        "width": 28,
        "height": 13
      }
    },
    {
      "type": "punctum",
      "bbox": {
        "x": 1341,
        "y": 1090,
        "width": 45,
        "height": 14
      }
    },
    {
      "type": "punctum",
      "bbox": {
        "x": 2065,
        "y": 2247,
        "width": 21,
        "height": 10
      }
    },
    {
      "type": "punctum",
      "bbox": {
        "x": 2659,
        "y": 2426,
        "width": 21,
        "height": 9
      }
    },
    {
      "type": "punctum",
      "bbox": {
        "x": 2074,
        "y": 1466,
        "width": 21,
        "height": 10
      }
    },
    {
      "type": "punctum",
      "bbox": {
        "x": 2475,
        "y": 3551,
        "width": 23,
        "height": 12
      }
    },
    {
      "type": "punctum",
      "bbox": {
        "x": 1553,
        "y": 1101,
        "width": 22,
        "height": 12
      }
    },
    {
      "type": "punctum",
      "bbox": {
        "x": 2544,
        "y": 3200,
        "width": 20,
        "height": 11
      }
    },
    {
      "type": "punctum",
      "bbox": {
        "x": 2304,
        "y": 702,
        "width": 23,
        "height": 11
      }
    },
    {
      "type": "punctum",
      "bbox": {
        "x": 1563,
        "y": 2790,
        "width": 18,
        "height": 12
      }
    },
    {
      "type": "punctum",
      "bbox": {
        "x": 2040,
        "y": 3379,
        "width": 20,
        "height": 10
      }
    },
    {
      "type": "punctum",
      "bbox": {
        "x": 1765,
        "y": 2231,
        "width": 25,
        "height": 9
      }
    },
    {
      "type": "punctum",
      "bbox": {
        "x": 2279,
        "y": 3369,
        "width": 18,
        "height": 11
      }
    },
    {
      "type": "punctum",
      "bbox": {
        "x": 2187,
        "y": 2233,
        "width": 21,
        "height": 12
      }
    },
    {
      "type": "virga",
      "bbox": {
        "x": 2603,
        "y": 2674,
        "width": 39,
        "height": 22
      }
    },
    {
      "type": "clivis",
      "bbox": {
        "x": 2007,
        "y": 3286,
        "width": 56,
        "height": 33
      }
    },
    {
      "type": "clivis",
      "bbox": {
        "x": 2018,
        "y": 2759,
        "width": 34,
        "height": 35
      }
    },
    {
      "type": "clivis",
      "bbox": {
        "x": 2359,
        "y": 807,
        "width": 43,
        "height": 46
      }
    },
    {
      "type": "clivis",
      "bbox": {
        "x": 1981,
        "y": 2573,
        "width": 36,
        "height": 37
      }
    },
    {
      "type": "clivis",
      "bbox": {
        "x": 2210,
        "y": 819,
        "width": 31,
        "height": 36
      }
    },
    {
      "type": "clivis",
      "bbox": {
        "x": 2776,
        "y": 680,
        "width": 35,
        "height": 31
      }
    },
    {
      "type": "clivis",
      "bbox": {
        "x": 2667,
        "y": 2208,
        "width": 34,
        "height": 34
      }
    },
    {
      "type": "clivis",
      "bbox": {
        "x": 2223,
        "y": 1054,
        "width": 33,
        "height": 36
      }
    },
    {
      "type": "clivis",
      "bbox": {
        "x": 2958,
        "y": 2124,
        "width": 34,
        "height": 37
      }
    },
    {
      "type": "clivis",
      "bbox": {
        "x": 2316,
        "y": 2198,
        "width": 30,
        "height": 37
      }
    },
    {
      "type": "clivis",
      "bbox": {
        "x": 2794,
        "y": 1087,
        "width": 35,
        "height": 37
      }
    },
    {
      "type": "clivis",
      "bbox": {
        "x": 2799,
        "y": 1194,
        "width": 32,
        "height": 36
      }
    },
    {
      "type": "clivis",
      "bbox": {
        "x": 1857,
        "y": 2575,
        "width": 82,
        "height": 34
      }
    },
    {
      "type": "climacus",
      "bbox": {
        "x": 2186,
        "y": 1262,
        "width": 51,
        "height": 50
      }
    },
    {
      "type": "climacus",
      "bbox": {
        "x": 2738,
        "y": 990,
        "width": 58,
        "height": 58
      }
    },
    {
      "type": "climacus",
      "bbox": {
        "x": 2647,
        "y": 870,
        "width": 52,
        "height": 54
      }
    },
    {
      "type": "climacus",
      "bbox": {
        "x": 2786,
        "y": 1263,
        "width": 54,
        "height": 68
      }
    },
    {
      "type": "climacus",
      "bbox": {
        "x": 2394,
        "y": 868,
        "width": 42,
        "height": 47
      }
    },
    {
      "type": "climacus",
      "bbox": {
        "x": 2843,
        "y": 2393,
        "width": 40,
        "height": 49
      }
    },
    {
      "type": "climacus",
      "bbox": {
        "x": 2683,
        "y": 659,
        "width": 47,
        "height": 48
      }
    },
    {
      "type": "climacus",
      "bbox": {
        "x": 2764,
        "y": 860,
        "width": 60,
        "height": 56
      }
    },
    {
      "type": "climacus",
      "bbox": {
        "x": 2052,
        "y": 1043,
        "width": 50,
        "height": 54
      }
    },
    {
      "type": "climacus",
      "bbox": {
        "x": 1816,
        "y": 2939,
        "width": 54,
        "height": 50
      }
    },
    {
      "type": "climacus",
      "bbox": {
        "x": 2669,
        "y": 998,
        "width": 46,
        "height": 51
      }
    },
    {
      "type": "climacus",
      "bbox": {
        "x": 3021,
        "y": 923,
        "width": 50,
        "height": 65
      }
    },
    {
      "type": "climacus",
      "bbox": {
        "x": 2416,
        "y": 2202,
        "width": 42,
        "height": 50
      }
    },
    {
      "type": "climacus",
      "bbox": {
        "x": 1849,
        "y": 3136,
        "width": 59,
        "height": 55
      }
    },
    {
      "type": "climacus",
      "bbox": {
        "x": 2052,
        "y": 838,
        "width": 48,
        "height": 54
      }
    },
    {
      "type": "climacus",
      "bbox": {
        "x": 1936,
        "y": 2752,
        "width": 46,
        "height": 49
      }
    },
    {
      "type": "climacus",
      "bbox": {
        "x": 2848,
        "y": 872,
        "width": 49,
        "height": 50
      }
    },
    {
      "type": "climacus",
      "bbox": {
        "x": 2135,
        "y": 1051,
        "width": 53,
        "height": 46
      }
    },
    {
      "type": "climacus",
      "bbox": {
        "x": 2340,
        "y": 2900,
        "width": 42,
        "height": 50
      }
    },
    {
      "type": "climacus",
      "bbox": {
        "x": 2163,
        "y": 1425,
        "width": 48,
        "height": 52
      }
    },
    {
      "type": "climacus",
      "bbox": {
        "x": 1865,
        "y": 2746,
        "width": 48,
        "height": 58
      }
    },
    {
      "type": "climacus",
      "bbox": {
        "x": 1975,
        "y": 832,
        "width": 52,
        "height": 52
      }
    },
    {
      "type": "climacus",
      "bbox": {
        "x": 1748,
        "y": 847,
        "width": 47,
        "height": 57
      }
    },
    {
      "type": "climacus",
      "bbox": {
        "x": 2166,
        "y": 609,
        "width": 45,
        "height": 50
      }
    },
    {
      "type": "pes subbipunctis",
      "bbox": {
        "x": 1619,
        "y": 1456,
        "width": 49,
        "height": 51
      }
    },
    {
      "type": "pes subbipunctis",
      "bbox": {
        "x": 2139,
        "y": 2548,
        "width": 55,
        "height": 54
      }
    },
    {
      "type": "pes subbipunctis",
      "bbox": {
        "x": 2025,
        "y": 2561,
        "width": 47,
        "height": 51
      }
    },
    {
      "type": "climacus",
      "bbox": {
        "x": 2608,
        "y": 1416,
        "width": 45,
        "height": 52
      }
    },
    {
      "type": "climacus",
      "bbox": {
        "x": 2443,
        "y": 3138,
        "width": 44,
        "height": 54
      }
    },
    {
      "type": "climacus",
      "bbox": {
        "x": 2726,
        "y": 1189,
        "width": 49,
        "height": 47
      }
    },
    {
      "type": "pes",
      "bbox": {
        "x": 2290,
        "y": 1432,
        "width": 46,
        "height": 47
      }
    },
    {
      "type": "pes quadratus",
      "bbox": {
        "x": 2850,
        "y": 681,
        "width": 70,
        "height": 39
      }
    },
    {
      "type": "pes",
      "bbox": {
        "x": 1752,
        "y": 2748,
        "width": 58,
        "height": 46
      }
    },
    {
      "type": "pes",
      "bbox": {
        "x": 2890,
        "y": 2958,
        "width": 57,
        "height": 44
      }
    },
    {
      "type": "pes",
      "bbox": {
        "x": 1903,
        "y": 1038,
        "width": 60,
        "height": 49
      }
    },
    {
      "type": "pes",
      "bbox": {
        "x": 1990,
        "y": 1443,
        "width": 52,
        "height": 44
      }
    },
    {
      "type": "pes",
      "bbox": {
        "x": 1610,
        "y": 1455,
        "width": 56,
        "height": 31
      }
    },
    {
      "type": "pes",
      "bbox": {
        "x": 1735,
        "y": 1045,
        "width": 56,
        "height": 48
      }
    },
    {
      "type": "pes",
      "bbox": {
        "x": 2524,
        "y": 2398,
        "width": 49,
        "height": 42
      }
    },
    {
      "type": "virga",
      "bbox": {
        "x": 2966,
        "y": 2969,
        "width": 39,
        "height": 34
      }
    },
    {
      "type": "virga",
      "bbox": {
        "x": 1678,
        "y": 2761,
        "width": 35,
        "height": 36
      }
    },
    {
      "type": "virga",
      "bbox": {
        "x": 2894,
        "y": 988,
        "width": 34,
        "height": 30
      }
    },
    {
      "type": "virga",
      "bbox": {
        "x": 2802,
        "y": 2970,
        "width": 42,
        "height": 32
      }
    },
    {
      "type": "virga",
      "bbox": {
        "x": 2549,
        "y": 2982,
        "width": 35,
        "height": 29
      }
    },
    {
      "type": "virga",
      "bbox": {
        "x": 2673,
        "y": 3176,
        "width": 35,
        "height": 32
      }
    },
    {
      "type": "virga",
      "bbox": {
        "x": 2635,
        "y": 2974,
        "width": 42,
        "height": 32
      }
    },
    {
      "type": "virga",
      "bbox": {
        "x": 1820,
        "y": 1056,
        "width": 38,
        "height": 37
      }
    },
    {
      "type": "virga",
      "bbox": {
        "x": 1709,
        "y": 664,
        "width": 47,
        "height": 38
      }
    },
    {
      "type": "virga",
      "bbox": {
        "x": 2467,
        "y": 2987,
        "width": 33,
        "height": 29
      }
    },
    {
      "type": "virga",
      "bbox": {
        "x": 2819,
        "y": 2644,
        "width": 36,
        "height": 35
      }
    },
    {
      "type": "virga",
      "bbox": {
        "x": 2225,
        "y": 1435,
        "width": 31,
        "height": 35
      }
    },
    {
      "type": "virga",
      "bbox": {
        "x": 2350,
        "y": 3163,
        "width": 37,
        "height": 35
      }
    },
    {
      "type": "quilismatorculus cum episema",
      "bbox": {
        "x": 2656,
        "y": 2629,
        "width": 93,
        "height": 57
      }
    },
    {
      "type": "quilismapes cum episema subbipunctis",
      "bbox": {
        "x": 2918,
        "y": 2753,
        "width": 89,
        "height": 66
      }
    },
    {
      "type": "pressus",
      "bbox": {
        "x": 2265,
        "y": 1260,
        "width": 56,
        "height": 50
      }
    },
    {
      "type": "pressus",
      "bbox": {
        "x": 2222,
        "y": 2559,
        "width": 48,
        "height": 50
      }
    },
    {
      "type": "bivirga episamata",
      "bbox": {
        "x": 1795,
        "y": 1415,
        "width": 51,
        "height": 57
      }
    },
    {
      "type": "pressus",
      "bbox": {
        "x": 2343,
        "y": 1240,
        "width": 60,
        "height": 58
      }
    },
    {
      "type": "pressus",
      "bbox": {
        "x": 1949,
        "y": 2938,
        "width": 55,
        "height": 55
      }
    },
    {
      "type": "equaliter",
      "bbox": {
        "x": 1575,
        "y": 2220,
        "width": 27,
        "height": 21
      }
    },
    {
      "type": "celeriter",
      "bbox": {
        "x": 2544,
        "y": 687,
        "width": 14,
        "height": 14
      }
    },
    {
      "type": "virga episema",
      "bbox": {
        "x": 2414,
        "y": 1228,
        "width": 39,
        "height": 41
      }
    },
    {
      "type": "virga episema",
      "bbox": {
        "x": 2030,
        "y": 2925,
        "width": 43,
        "height": 43
      }
    },
    {
      "type": "virga episema",
      "bbox": {
        "x": 2814,
        "y": 1001,
        "width": 40,
        "height": 40
      }
    },
    {
      "type": "virga episema",
      "bbox": {
        "x": 1684,
        "y": 1448,
        "width": 51,
        "height": 42
      }
    },
    {
      "type": "virga episema",
      "bbox": {
        "x": 2948,
        "y": 2212,
        "width": 59,
        "height": 43
      }
    },
    {
      "type": "clivis episema",
      "bbox": {
        "x": 1906,
        "y": 844,
        "width": 54,
        "height": 44
      }
    },
    {
      "type": "porrectus",
      "bbox": {
        "x": 2006,
        "y": 3286,
        "width": 58,
        "height": 33
      }
    },
    {
      "type": "clivis episema",
      "bbox": {
        "x": 2401,
        "y": 3511,
        "width": 40,
        "height": 37
      }
    },
    {
      "type": "clivis episema",
      "bbox": {
        "x": 1912,
        "y": 1405,
        "width": 50,
        "height": 41
      }
    },
    {
      "type": "clivis episema",
      "bbox": {
        "x": 2138,
        "y": 1271,
        "width": 43,
        "height": 41
      }
    },
    {
      "type": "clivis episema",
      "bbox": {
        "x": 2192,
        "y": 3104,
        "width": 42,
        "height": 39
      }
    },
    {
      "type": "clivis",
      "bbox": {
        "x": 1748,
        "y": 1439,
        "width": 32,
        "height": 36
      }
    },
    {
      "type": "unknown",
      "bbox": {
        "x": 1858,
        "y": 1422,
        "width": 44,
        "height": 40
      }
    },
    {
      "type": "punctum",
      "bbox": {
        "x": 1889,
        "y": 1482,
        "width": 20,
        "height": 11
      }
    },
    {
      "type": "tractulus episema",
      "bbox": {
        "x": 2140,
        "y": 1460,
        "width": 34,
        "height": 20
      }
    },
    {
      "type": "unknown",
      "bbox": {
        "x": 2487,
        "y": 1225,
        "width": 41,
        "height": 23
      }
    },
    {
      "type": "pressus",
      "bbox": {
        "x": 2544,
        "y": 1223,
        "width": 40,
        "height": 27
      }
    },
    {
      "type": "scandicus climacus",
      "bbox": {
        "x": 2618,
        "y": 1198,
        "width": 88,
        "height": 46
      }
    },
    {
      "type": "punctum",
      "bbox": {
        "x": 2477,
        "y": 1325,
        "width": 21,
        "height": 10
      }
    },
    {
      "type": "tractulus episema",
      "bbox": {
        "x": 2574,
        "y": 1455,
        "width": 25,
        "height": 16
      }
    },
    {
      "type": "pes-quassus",
      "bbox": {
        "x": 2673,
        "y": 1426,
        "width": 65,
        "height": 40
      }
    },
    {
      "type": "bivirga",
      "bbox": {
        "x": 2605,
        "y": 1282,
        "width": 49,
        "height": 37
      }
    },
    {
      "type": "pes liquescens",
      "bbox": {
        "x": 2695,
        "y": 1286,
        "width": 21,
        "height": 18
      }
    },
    {
      "type": "pes subbipunctis",
      "bbox": {
        "x": 2862,
        "y": 1269,
        "width": 61,
        "height": 51
      }
    },
    {
      "type": "pes-quassus",
      "bbox": {
        "x": 2930,
        "y": 1287,
        "width": 56,
        "height": 35
      }
    },
    {
      "type": "scandicus climacus",
      "bbox": {
        "x": 2994,
        "y": 1258,
        "width": 83,
        "height": 55
      }
    },
    {
      "type": "virga",
      "bbox": {
        "x": 1580,
        "y": 2402,
        "width": 34,
        "height": 36
      }
    },
    {
      "type": "torculus",
      "bbox": {
        "x": 1680,
        "y": 2375,
        "width": 43,
        "height": 47
      }
    },
    {
      "type": "sursum",
      "bbox": {
        "x": 1712,
        "y": 2336,
        "width": 19,
        "height": 28
      }
    },
    {
      "type": "clivis episema",
      "bbox": {
        "x": 1831,
        "y": 2371,
        "width": 41,
        "height": 36
      }
    },
    {
      "type": "clivis episema",
      "bbox": {
        "x": 1875,
        "y": 2364,
        "width": 33,
        "height": 37
      }
    },
    {
      "type": "clivis episema",
      "bbox": {
        "x": 1962,
        "y": 2386,
        "width": 43,
        "height": 37
      }
    },
    {
      "type": "quilisma",
      "bbox": {
        "x": 1994,
        "y": 2388,
        "width": 60,
        "height": 27
      }
    },
    {
      "type": "clivis episema",
      "bbox": {
        "x": 2071,
        "y": 2359,
        "width": 42,
        "height": 41
      }
    },
    {
      "type": "celeriter",
      "bbox": {
        "x": 2114,
        "y": 2359,
        "width": 25,
        "height": 32
      }
    },
    {
      "type": "clivis",
      "bbox": {
        "x": 2112,
        "y": 2419,
        "width": 30,
        "height": 36
      }
    },
    {
      "type": "virga episema",
      "bbox": {
        "x": 2150,
        "y": 2411,
        "width": 34,
        "height": 33
      }
    },
    {
      "type": "pes subbipunctis",
      "bbox": {
        "x": 2192,
        "y": 2387,
        "width": 51,
        "height": 64
      }
    },
    {
      "type": "virga",
      "bbox": {
        "x": 2253,
        "y": 2391,
        "width": 35,
        "height": 34
      }
    },
    {
      "type": "punctum",
      "bbox": {
        "x": 2379,
        "y": 2430,
        "width": 21,
        "height": 11
      }
    },
    {
      "type": "cephalicus",
      "bbox": {
        "x": 2904,
        "y": 2392,
        "width": 31,
        "height": 48
      }
    },
    {
      "type": "pes liquescens",
      "bbox": {
        "x": 1586,
        "y": 687,
        "width": 34,
        "height": 25
      }
    },
    {
      "type": "cephalicus",
      "bbox": {
        "x": 1808,
        "y": 661,
        "width": 37,
        "height": 50
      }
    },
    {
      "type": "bistropha",
      "bbox": {
        "x": 2053,
        "y": 645,
        "width": 32,
        "height": 18
      }
    },
    {
      "type": "clivis",
      "bbox": {
        "x": 2105,
        "y": 621,
        "width": 41,
        "height": 34
      }
    },
    {
      "type": "celeriter",
      "bbox": {
        "x": 2220,
        "y": 598,
        "width": 14,
        "height": 17
      }
    },
    {
      "type": "trigon",
      "bbox": {
        "x": 2242,
        "y": 617,
        "width": 33,
        "height": 25
      }
    },
    {
      "type": "clivis",
      "bbox": {
        "x": 2298,
        "y": 601,
        "width": 32,
        "height": 36
      }
    },
    {
      "type": "equaliter",
      "bbox": {
        "x": 2392,
        "y": 698,
        "width": 24,
        "height": 18
      }
    },
    {
      "type": "punctum",
      "bbox": {
        "x": 2499,
        "y": 698,
        "width": 20,
        "height": 10
      }
    },
    {
      "type": "trigon",
      "bbox": {
        "x": 1830,
        "y": 864,
        "width": 35,
        "height": 27
      }
    },
    {
      "type": "clivis",
      "bbox": {
        "x": 1618,
        "y": 882,
        "width": 35,
        "height": 35
      }
    },
    {
      "type": "pes",
      "bbox": {
        "x": 2137,
        "y": 827,
        "width": 55,
        "height": 45
      }
    },
    {
      "type": "bivirga",
      "bbox": {
        "x": 2265,
        "y": 807,
        "width": 57,
        "height": 57
      }
    },
    {
      "type": "clivis episema",
      "bbox": {
        "x": 2429,
        "y": 802,
        "width": 50,
        "height": 39
      }
    },
    {
      "type": "salicus",
      "bbox": {
        "x": 2301,
        "y": 880,
        "width": 87,
        "height": 73
      }
    },
    {
      "type": "porrectus",
      "bbox": {
        "x": 2451,
        "y": 868,
        "width": 51,
        "height": 34
      }
    },
    {
      "type": "clivis",
      "bbox": {
        "x": 2483,
        "y": 894,
        "width": 34,
        "height": 30
      }
    },
    {
      "type": "pes-quassus",
      "bbox": {
        "x": 2513,
        "y": 889,
        "width": 58,
        "height": 36
      }
    },
    {
      "type": "clivis",
      "bbox": {
        "x": 2606,
        "y": 890,
        "width": 32,
        "height": 30
      }
    },
    {
      "type": "clivis",
      "bbox": {
        "x": 2724,
        "y": 881,
        "width": 32,
        "height": 32
      }
    },
    {
      "type": "pes",
      "bbox": {
        "x": 1637,
        "y": 1056,
        "width": 55,
        "height": 48
      }
    },
    {
      "type": "bistropha",
      "bbox": {
        "x": 2337,
        "y": 1051,
        "width": 34,
        "height": 18
      }
    },
    {
      "type": "porrectus",
      "bbox": {
        "x": 2420,
        "y": 1022,
        "width": 123,
        "height": 51
      }
    },
    {
      "type": "quilismatorculus",
      "bbox": {
        "x": 2939,
        "y": 942,
        "width": 79,
        "height": 55
      }
    },
    {
      "type": "stropha",
      "bbox": {
        "x": 2302,
        "y": 1080,
        "width": 17,
        "height": 16
      }
    },
    {
      "type": "quilisma",
      "bbox": {
        "x": 2335,
        "y": 2564,
        "width": 70,
        "height": 32
      }
    },
    {
      "type": "virga",
      "bbox": {
        "x": 2427,
        "y": 2543,
        "width": 41,
        "height": 31
      }
    },
    {
      "type": "bistropha",
      "bbox": {
        "x": 2099,
        "y": 2743,
        "width": 27,
        "height": 25
      }
    },
    {
      "type": "porrectus",
      "bbox": {
        "x": 2159,
        "y": 2695,
        "width": 109,
        "height": 60
      }
    },
    {
      "type": "scandicus climacus",
      "bbox": {
        "x": 2288,
        "y": 2683,
        "width": 82,
        "height": 52
      }
    },
    {
      "type": "climacus",
      "bbox": {
        "x": 2386,
        "y": 2681,
        "width": 48,
        "height": 44
      }
    },
    {
      "type": "pes subbipunctis",
      "bbox": {
        "x": 2458,
        "y": 2671,
        "width": 59,
        "height": 51
      }
    },
    {
      "type": "virga",
      "bbox": {
        "x": 2532,
        "y": 2685,
        "width": 31,
        "height": 28
      }
    },
    {
      "type": "climacus",
      "bbox": {
        "x": 2760,
        "y": 2626,
        "width": 53,
        "height": 56
      }
    },
    {
      "type": "porrectus",
      "bbox": {
        "x": 1915,
        "y": 2211,
        "width": 56,
        "height": 32
      }
    },
    {
      "type": "climacus",
      "bbox": {
        "x": 1987,
        "y": 2182,
        "width": 42,
        "height": 45
      }
    },
    {
      "type": "pes liquescens",
      "bbox": {
        "x": 1640,
        "y": 2227,
        "width": 26,
        "height": 21
      }
    },
    {
      "type": "punctum",
      "bbox": {
        "x": 1529,
        "y": 2236,
        "width": 18,
        "height": 10
      }
    },
    {
      "type": "salicus",
      "bbox": {
        "x": 2356,
        "y": 2159,
        "width": 93,
        "height": 75
      }
    },
    {
      "type": "porrectus subbipunctis",
      "bbox": {
        "x": 2481,
        "y": 2225,
        "width": 50,
        "height": 47
      }
    },
    {
      "type": "clivis",
      "bbox": {
        "x": 2551,
        "y": 2227,
        "width": 27,
        "height": 30
      }
    },
    {
      "type": "porrectus",
      "bbox": {
        "x": 2583,
        "y": 2220,
        "width": 49,
        "height": 31
      }
    },
    {
      "type": "climacus",
      "bbox": {
        "x": 2775,
        "y": 2171,
        "width": 32,
        "height": 48
      }
    },
    {
      "type": "scandicus",
      "bbox": {
        "x": 2713,
        "y": 2168,
        "width": 75,
        "height": 60
      }
    },
    {
      "type": "quilisma",
      "bbox": {
        "x": 2863,
        "y": 2161,
        "width": 71,
        "height": 25
      }
    },
    {
      "type": "oriscus",
      "bbox": {
        "x": 2985,
        "y": 2125,
        "width": 36,
        "height": 50
      }
    },
    {
      "type": "torculus",
      "bbox": {
        "x": 3031,
        "y": 2109,
        "width": 41,
        "height": 33
      }
    },
    {
      "type": "porrectus",
      "bbox": {
        "x": 2057,
        "y": 2179,
        "width": 49,
        "height": 36
      }
    },
    {
      "type": "virga",
      "bbox": {
        "x": 2122,
        "y": 2153,
        "width": 38,
        "height": 33
      }
    },
    {
      "type": "bivirga",
      "bbox": {
        "x": 2592,
        "y": 656,
        "width": 57,
        "height": 40
      }
    },
    {
      "type": "scandicus climacus",
      "bbox": {
        "x": 2552,
        "y": 997,
        "width": 89,
        "height": 68
      }
    },
    {
      "type": "punctum",
      "bbox": {
        "x": 1611,
        "y": 1299,
        "width": 22,
        "height": 9
      }
    },
    {
      "type": "quilisma",
      "bbox": {
        "x": 1643,
        "y": 1254,
        "width": 89,
        "height": 53
      }
    },
    {
      "type": "quilisma",
      "bbox": {
        "x": 1753,
        "y": 1229,
        "width": 95,
        "height": 67
      }
    },
    {
      "type": "pes liquescens",
      "bbox": {
        "x": 1955,
        "y": 1305,
        "width": 28,
        "height": 21
      }
    },
    {
      "type": "porrectus subbipunctis",
      "bbox": {
        "x": 2650,
        "y": 3345,
        "width": 61,
        "height": 50
      }
    },
    {
      "type": "clivis episema",
      "bbox": {
        "x": 2952,
        "y": 3489,
        "width": 54,
        "height": 60
      }
    },
    {
      "type": "celeriter",
      "bbox": {
        "x": 3007,
        "y": 3483,
        "width": 28,
        "height": 42
      }
    },
    {
      "type": "pes liquescens",
      "bbox": {
        "x": 2677,
        "y": 3525,
        "width": 35,
        "height": 30
      }
    },
    {
      "type": "torculus",
      "bbox": {
        "x": 2236,
        "y": 3519,
        "width": 46,
        "height": 37
      }
    },
    {
      "type": "bivirga",
      "bbox": {
        "x": 2147,
        "y": 3522,
        "width": 57,
        "height": 45
      }
    },
    {
      "type": "torculus",
      "bbox": {
        "x": 2006,
        "y": 3466,
        "width": 45,
        "height": 36
      }
    },
    {
      "type": "oriscus",
      "bbox": {
        "x": 1962,
        "y": 3479,
        "width": 33,
        "height": 42
      }
    },
    {
      "type": "clivis",
      "bbox": {
        "x": 1927,
        "y": 3483,
        "width": 35,
        "height": 48
      }
    },
    {
      "type": "quilisma",
      "bbox": {
        "x": 1823,
        "y": 3521,
        "width": 66,
        "height": 23
      }
    },
    {
      "type": "punctum",
      "bbox": {
        "x": 1790,
        "y": 3537,
        "width": 24,
        "height": 12
      }
    },
    {
      "type": "scandicus climacus",
      "bbox": {
        "x": 1651,
        "y": 3500,
        "width": 108,
        "height": 76
      }
    },
    {
      "type": "pes",
      "bbox": {
        "x": 1638,
        "y": 3332,
        "width": 54,
        "height": 41
      }
    },
    {
      "type": "punctum",
      "bbox": {
        "x": 1540,
        "y": 3371,
        "width": 20,
        "height": 14
      }
    },
    {
      "type": "levare",
      "bbox": {
        "x": 1548,
        "y": 3334,
        "width": 13,
        "height": 20
      }
    },
    {
      "type": "virga",
      "bbox": {
        "x": 1733,
        "y": 3345,
        "width": 36,
        "height": 31
      }
    },
    {
      "type": "porrectus",
      "bbox": {
        "x": 1866,
        "y": 3327,
        "width": 56,
        "height": 34
      }
    },
    {
      "type": "climacus",
      "bbox": {
        "x": 1937,
        "y": 3295,
        "width": 49,
        "height": 52
      }
    },
    {
      "type": "clivis",
      "bbox": {
        "x": 1991,
        "y": 3354,
        "width": 29,
        "height": 32
      }
    },
    {
      "type": "punctum",
      "bbox": {
        "x": 2171,
        "y": 3376,
        "width": 21,
        "height": 10
      }
    },
    {
      "type": "salicus",
      "bbox": {
        "x": 2463,
        "y": 3300,
        "width": 83,
        "height": 79
      }
    },
    {
      "type": "clivis",
      "bbox": {
        "x": 2424,
        "y": 3342,
        "width": 34,
        "height": 42
      }
    },
    {
      "type": "climacus",
      "bbox": {
        "x": 2538,
        "y": 3348,
        "width": 49,
        "height": 38
      }
    },
    {
      "type": "clivis episema",
      "bbox": {
        "x": 2141,
        "y": 3119,
        "width": 36,
        "height": 44
      }
    },
    {
      "type": "salicus",
      "bbox": {
        "x": 2229,
        "y": 3136,
        "width": 96,
        "height": 78
      }
    },
    {
      "type": "clivis",
      "bbox": {
        "x": 1999,
        "y": 3117,
        "width": 37,
        "height": 37
      }
    },
    {
      "type": "pes",
      "bbox": {
        "x": 1929,
        "y": 3124,
        "width": 52,
        "height": 44
      }
    },
    {
      "type": "pes subbipunctis",
      "bbox": {
        "x": 1625,
        "y": 3113,
        "width": 55,
        "height": 63
      }
    },
    {
      "type": "pes-quassus",
      "bbox": {
        "x": 1691,
        "y": 3134,
        "width": 54,
        "height": 36
      }
    },
    {
      "type": "scandicus climacus",
      "bbox": {
        "x": 1761,
        "y": 3091,
        "width": 81,
        "height": 61
      }
    },
    {
      "type": "climacus",
      "bbox": {
        "x": 1549,
        "y": 3128,
        "width": 53,
        "height": 70
      }
    },
    {
      "type": "pes liquescens",
      "bbox": {
        "x": 1578,
        "y": 2981,
        "width": 43,
        "height": 23
      }
    },
    {
      "type": "clivis episema",
      "bbox": {
        "x": 1767,
        "y": 2948,
        "width": 47,
        "height": 42
      }
    },
    {
      "type": "pressus",
      "bbox": {
        "x": 1886,
        "y": 2961,
        "width": 43,
        "height": 27
      }
    },
    {
      "type": "stropha",
      "bbox": {
        "x": 2102,
        "y": 2927,
        "width": 15,
        "height": 19
      }
    },
    {
      "type": "levare",
      "bbox": {
        "x": 2121,
        "y": 2925,
        "width": 18,
        "height": 23
      }
    },
    {
      "type": "pressus",
      "bbox": {
        "x": 2171,
        "y": 2922,
        "width": 39,
        "height": 27
      }
    },
    {
      "type": "scandicus climacus",
      "bbox": {
        "x": 2247,
        "y": 2896,
        "width": 84,
        "height": 60
      }
    },
    {
      "type": "clivis",
      "bbox": {
        "x": 2407,
        "y": 2910,
        "width": 35,
        "height": 33
      }
    },
    {
      "type": "bivirga",
      "bbox": {
        "x": 2386,
        "y": 2969,
        "width": 51,
        "height": 57
      }
    },
    {
      "type": "punctum",
      "bbox": {
        "x": 2242,
        "y": 3012,
        "width": 24,
        "height": 11
      }
    },
    {
      "type": "climacus",
      "bbox": {
        "x": 2059,
        "y": 3099,
        "width": 66,
        "height": 60
      }
    },
    {
      "type": "punctum",
      "bbox": {
        "x": 2389,
        "y": 3175,
        "width": 38,
        "height": 24
      }
    },
    {
      "type": "virga",
      "bbox": {
        "x": 2503,
        "y": 3141,
        "width": 34,
        "height": 43
      }
    },
    {
      "type": "clivis episema",
      "bbox": {
        "x": 2478,
        "y": 2788,
        "width": 51,
        "height": 40
      }
    },
    {
      "type": "quilisma",
      "bbox": {
        "x": 2830,
        "y": 2769,
        "width": 79,
        "height": 50
      }
    },
    {
      "type": "punctum",
      "bbox": {
        "x": 2804,
        "y": 2806,
        "width": 21,
        "height": 10
      }
    },
    {
      "type": "clivis",
      "bbox": {
        "x": 2793,
        "y": 3162,
        "width": 33,
        "height": 34
      }
    },
    {
      "type": "celeriter",
      "bbox": {
        "x": 2833,
        "y": 3161,
        "width": 24,
        "height": 27
      }
    },
    {
      "type": "climacus",
      "bbox": {
        "x": 2953,
        "y": 3145,
        "width": 39,
        "height": 60
      }
    },
    {
      "type": "unknown",
      "bbox": {
        "x": 3002,
        "y": 3163,
        "width": 40,
        "height": 36
      }
    },
    {
      "type": "tractulus episema",
      "bbox": {
        "x": 2922,
        "y": 3179,
        "width": 23,
        "height": 19
      }
    },
    {
      "type": "clivis",
      "bbox": {
        "x": 2095,
        "y": 2567,
        "width": 34,
        "height": 37
      }
    },
    {
      "type": "punctum",
      "bbox": {
        "x": 2309,
        "y": 2594,
        "width": 18,
        "height": 11
      }
    },
    {
      "type": "clivis episema",
      "bbox": {
        "x": 2359,
        "y": 3509,
        "width": 39,
        "height": 49
      }
    },
    {
      "type": "clivis",
      "bbox": {
        "x": 2845,
        "y": 3343,
        "width": 33,
        "height": 33
      }
    },
    {
      "type": "porrectus",
      "bbox": {
        "x": 2879,
        "y": 3336,
        "width": 58,
        "height": 37
      }
    },
    {
      "type": "clivis",
      "bbox": {
        "x": 2449,
        "y": 1445,
        "width": 33,
        "height": 32
      }
    },
    {
      "type": "pes-quassus",
      "bbox": {
        "x": 2485,
        "y": 1442,
        "width": 49,
        "height": 30
      }
    }
  ]
}